octo_pipeline_python/backends/perl/__init__.py
octo_pipeline_python/backends/perl/perl_backend.py
octo_pipeline_python/backends/perl/actions/__init__.py
octo_pipeline_python/backends/perl/actions/perl_execute.py
octo_pipeline_python/backends/perl/models/__init__.py
octo_pipeline_python/backends/perl/models/perl_backend_model.py
octo_pipeline_backend_perl_python-1.3.2.dist-info/LICENSE.txt
octo_pipeline_backend_perl_python-1.3.2.dist-info/METADATA
octo_pipeline_backend_perl_python-1.3.2.dist-info/README.md
octo_pipeline_backend_perl_python-1.3.2.dist-info/WHEEL
octo_pipeline_backend_perl_python-1.3.2.dist-info/top_level.txt
octo_pipeline_backend_perl_python-1.3.2.dist-info/RECORD
